<annotation>
	<folder>Images</folder>
	<filename>00052.jpg</filename>
	<path>E:\Image-recognition\MyImages\10\Images\00052.jpg</path>
	<source>
		<database>Unknown</database>
	</source>
	<size>
		<width>2736</width>
		<height>3648</height>
		<depth>3</depth>
	</size>
	<segmented>0</segmented>
	<object>
		<name>LPT Section</name>
		<pose>Unspecified</pose>
		<truncated>0</truncated>
		<difficult>0</difficult>
		<bndbox>
			<xmin>1690</xmin>
			<ymin>432</ymin>
			<xmax>2466</xmax>
			<ymax>1312</ymax>
		</bndbox>
	</object>
	<object>
		<name>Fan Casing and Support</name>
		<pose>Unspecified</pose>
		<truncated>0</truncated>
		<difficult>0</difficult>
		<bndbox>
			<xmin>294</xmin>
			<ymin>104</ymin>
			<xmax>1718</xmax>
			<ymax>1416</ymax>
		</bndbox>
	</object>
	<object>
		<name>HPT Section</name>
		<pose>Unspecified</pose>
		<truncated>0</truncated>
		<difficult>0</difficult>
		<bndbox>
			<xmin>1686</xmin>
			<ymin>1444</ymin>
			<xmax>2186</xmax>
			<ymax>1912</ymax>
		</bndbox>
	</object>
	<object>
		<name>Bearing-6204</name>
		<pose>Unspecified</pose>
		<truncated>0</truncated>
		<difficult>0</difficult>
		<bndbox>
			<xmin>490</xmin>
			<ymin>1576</ymin>
			<xmax>834</xmax>
			<ymax>1908</ymax>
		</bndbox>
	</object>
	<object>
		<name>Bearing-6003</name>
		<pose>Unspecified</pose>
		<truncated>0</truncated>
		<difficult>0</difficult>
		<bndbox>
			<xmin>886</xmin>
			<ymin>1548</ymin>
			<xmax>1178</xmax>
			<ymax>1856</ymax>
		</bndbox>
	</object>
	<object>
		<name>Low Pressure Spool</name>
		<pose>Unspecified</pose>
		<truncated>0</truncated>
		<difficult>0</difficult>
		<bndbox>
			<xmin>1034</xmin>
			<ymin>1312</ymin>
			<xmax>1602</xmax>
			<ymax>1976</ymax>
		</bndbox>
	</object>
	<object>
		<name>Combustion Section</name>
		<pose>Unspecified</pose>
		<truncated>0</truncated>
		<difficult>0</difficult>
		<bndbox>
			<xmin>1570</xmin>
			<ymin>2004</ymin>
			<xmax>2258</xmax>
			<ymax>2496</ymax>
		</bndbox>
	</object>
	<object>
		<name>Nozzle Section</name>
		<pose>Unspecified</pose>
		<truncated>0</truncated>
		<difficult>0</difficult>
		<bndbox>
			<xmin>694</xmin>
			<ymin>1828</ymin>
			<xmax>1502</xmax>
			<ymax>2684</ymax>
		</bndbox>
	</object>
	<object>
		<name>High Pressure Spool</name>
		<pose>Unspecified</pose>
		<truncated>0</truncated>
		<difficult>0</difficult>
		<bndbox>
			<xmin>322</xmin>
			<ymin>2424</ymin>
			<xmax>1114</xmax>
			<ymax>3396</ymax>
		</bndbox>
	</object>
	<object>
		<name>Fan and Low Pressure Shaft</name>
		<pose>Unspecified</pose>
		<truncated>0</truncated>
		<difficult>0</difficult>
		<bndbox>
			<xmin>1158</xmin>
			<ymin>2224</ymin>
			<xmax>2374</xmax>
			<ymax>3596</ymax>
		</bndbox>
	</object>
</annotation>
